erp_visard/__init__.py
erp_visard/__main__.py
erp_visard/py.typed
erp_visard-0.0.1.dist-info/entry_points.txt
erp_visard-0.0.1.dist-info/LICENSE
erp_visard-0.0.1.dist-info/WHEEL
erp_visard-0.0.1.dist-info/METADATA
erp_visard-0.0.1.dist-info/RECORD
