Metadata-Version: 2.1
Name: erp-visard
Version: 0.0.1
Summary: ERP Visard
Home-page: https://github.com/sharlon.regales-tno/erp-visard
License: MIT
Author: TNO AGS Optimization
Author-email: sharlon.regales@tno.nl
Requires-Python: >=3.8,<4.0
Classifier: Development Status :: 3 - Alpha
Classifier: License :: OSI Approved :: MIT License
Classifier: Programming Language :: Python :: 3
Classifier: Programming Language :: Python :: 3.10
Classifier: Programming Language :: Python :: 3.8
Classifier: Programming Language :: Python :: 3.9
Requires-Dist: click (>=8.0.1)
Requires-Dist: dash (>=2.2.0,<3.0.0)
Requires-Dist: pandas (>=1.4.1,<2.0.0)
Requires-Dist: plotly (>=5.6.0,<6.0.0)
Project-URL: Changelog, https://github.com/sharlon.regales-tno/erp-visard/releases
Project-URL: Documentation, https://erp-visard.readthedocs.io
Project-URL: Repository, https://github.com/sharlon.regales-tno/erp-visard
